django_performance_testing/__init__.py
django_performance_testing/apps.py
django_performance_testing/context.py
django_performance_testing/core.py
django_performance_testing/models.py
django_performance_testing/queries.py
django_performance_testing/registry.py
django_performance_testing/reports.py
django_performance_testing/serializer.py
django_performance_testing/signals.py
django_performance_testing/templates.py
django_performance_testing/test_client.py
django_performance_testing/test_runner.py
django_performance_testing/timing.py
django_performance_testing/utils.py
django_performance_testing/management/__init__.py
django_performance_testing/management/commands/__init__.py
django_performance_testing/management/commands/djpt_worst_report.py
django_performance_testing/templatetags/__init__.py
django_performance_testing/templatetags/djpt_limits.py
django_performance_testing-0.7.3.dist-info/DESCRIPTION.rst
django_performance_testing-0.7.3.dist-info/METADATA
django_performance_testing-0.7.3.dist-info/RECORD
django_performance_testing-0.7.3.dist-info/WHEEL
django_performance_testing-0.7.3.dist-info/metadata.json
django_performance_testing-0.7.3.dist-info/top_level.txt
