Metadata-Version: 2.0
Name: django-performance-testing
Version: 0.7.3
Summary: Performance testing tools for Django
Home-page: https://github.com/PaesslerAG/django-performance-testing
Author: Paessler AG BIS Team
Author-email: bis@paessler.com
License: BSD
Keywords: django-performance-testing
Platform: UNKNOWN
Classifier: Development Status :: 4 - Beta
Classifier: Intended Audience :: Developers
Classifier: License :: OSI Approved :: BSD License
Classifier: Natural Language :: English
Classifier: Programming Language :: Python :: 2
Classifier: Programming Language :: Python :: 2.7
Classifier: Programming Language :: Python :: 3
Classifier: Programming Language :: Python :: 3.3
Classifier: Programming Language :: Python :: 3.4
Classifier: Programming Language :: Python :: 3.5
Classifier: Programming Language :: Python :: 3.6
Classifier: Framework :: Django
Classifier: Framework :: Django :: 1.8
Classifier: Framework :: Django :: 1.9
Classifier: Framework :: Django :: 1.10
Requires-Dist: Django (>=1.8)
